dbt/__init__.py
dbt/adapters/__init__.py
dbt/adapters/scandal/__init__.py
dbt/adapters/scandal/__version__.py
dbt/adapters/scandal/connections.py
dbt/adapters/scandal/impl.py
dbt/include/__init__.py
dbt/include/scandal/__init__.py
dbt/include/scandal/dbt_project.yml
dbt/include/scandal/macros/materializations/seeds/create_csv_table.sql
dbt/include/scandal/macros/materializations/seeds/load_csv_rows.sql
dbt/include/scandal/macros/materializations/seeds/reset_csv_table.sql
dbt/include/scandal/profile_template.yml
dbt_scandal-0.1.2.dist-info/METADATA
dbt_scandal-0.1.2.dist-info/WHEEL
dbt_scandal-0.1.2.dist-info/RECORD
