Metadata-Version: 2.1
Name: dbt-scandal
Version: 0.1.2
Summary: DBT adapter for scandal
Author: Robert Kruszewski
Author-email: github@robertk.io
Requires-Python: >=3.10,<4.0
Classifier: Programming Language :: Python :: 3
Classifier: Programming Language :: Python :: 3.10
Classifier: Programming Language :: Python :: 3.11
Requires-Dist: dbt-core (>=1.4.6,<1.5.0)
Requires-Dist: pandas (>=2.0.1,<3.0.0)
Requires-Dist: poetry (>=1.2.0)
Requires-Dist: pyarrow (>=12.0.0,<13.0.0)
Requires-Dist: scandal (>=0.1.1,<0.2.0)
